Workbook

Sheet Dashboard
A1: Portfolio Dashboard
B2: Asset Class | C2: Target Allocation (%) | D2: Actual Allocation (%) | E2: Difference
B3: Kenyan Stocks | C3: 50 | D3: =D19 -> 55.239831 | E3: =D3-C3 -> 5.2398312
B4: Treasury Bonds | C4: 30 | D4: =D20 -> 23.102042 | E4: =D4-C4 -> -6.8979577
B5: Foreign ETFs | C5: 15 | D5: =D21 -> 14.021088 | E5: =D5-C5 -> -0.97891229
B6: Cash/MMF | C6: 5 | D6: =D22 -> 7.6370388 | E6: =D6-C6 -> 2.6370388
B8: Kenyan-Stock Sector | C8: Target Allocation (%) | D8: Actual Allocation (%) | E8: Difference
B9: Banking | C9: 30 | D9: =C29 -> 32.572022 | E9: =D9-C9 -> 2.5720216
B10: Telecom | C10: 20 | D10: =C30 -> 16.954629 | E10: =D10-C10 -> -3.0453713
B11: Insurance | C11: 20 | D11: =C31 -> 22.778163 | E11: =D11-C11 -> 2.7781633
B12: Energy | C12: 30 | D12: =C32 -> 27.695186 | E12: =D12-C12 -> -2.3048136
A17: Present State
B18: Asset Class | C18: Value (Kshs.) | D18: Percentage | E18: Average Interest
B19: Kenyan Stocks | C19: =Holdings!C43 -> 14466296 | D19: =SUM(Holdings!D35:'Holdings'!D38) -> 55.239831 | E19: 0.095
B20: Treasury Bonds | C20: =Holdings!C40 -> 6050000 | D20: =Holdings!D40 -> 23.102042 | E20: 0.145
B21: Foreign ETFs | C21: =Holdings!C39 -> 3671865 | D21: =Holdings!D39 -> 14.021088 | E21: 0.0105
B22: Cash/MMF | C22: =Holdings!C41 -> 2000000 | D22: =Holdings!D41 -> 7.6370388 | E22: 0.105
B28: Kenyan-Stock Sector | C28: Percentage
B29: Banking | C29: =Holdings!C35/C19*100 -> 32.572022
B30: Telecom | C30: =Holdings!C36/C19*100 -> 16.954629
B31: Insurance | C31: =Holdings!C37/C19*100 -> 22.778163
B32: Energy | C32: =Holdings!C38/C19*100 -> 27.695186

Sheet Holdings
A1: Asset Value
A2: Asset | B2: Sector | C2: Target % | D2: Shares | E2: Shares Percentage | F2: Buy Price | G2: Current Price | H2: Cost Value | I2: Market Value | J2: Gain/Loss
A3: Banking
A4: Co-op Bank | B4: Banking | C4: 5 | D4: 33000 | E4: =H4/(SUM(H4:H7))*100 -> 22.481067 | F4: 32.1 | G4: =F4+2 -> 34.1 | H4: =D4*F4 -> 1059300 | I4: =D4*G4 -> 1125300 | J4: =I4-H4 -> 66000
A5: Equity | B5: Banking | C5: 5 | D5: 15000 | E5: =H5/(SUM(H4:H7))*100 -> 23.636636 | F5: 74.25 | G5: =F5+2 -> 76.25 | H5: =D5*F5 -> 1113750 | I5: =D5*G5 -> 1143750 | J5: =I5-H5 -> 30000
A6: KCB | B6: Banking | C6: 5 | D6: 18900 | E6: =H6/(SUM(H4:H7))*100 -> 26.773862 | F6: 66.75 | G6: =F6+2 -> 68.75 | H6: =D6*F6 -> 1261575 | I6: =D6*G6 -> 1299375 | J6: =I6-H6 -> 37800
A7: NCBA | B7: Banking | C7: 5 | D7: 14640 | E7: =H7/(SUM(H4:H7))*100 -> 27.108436 | F7: 87.25 | G7: =F7+2 -> 89.25 | H7: =D7*F7 -> 1277340 | I7: =D7*G7 -> 1306620 | J7: =I7-H7 -> 29280
A9: Telecommunication
A10: Safaricom | B10: Telecom | C10: 10 | D10: 80285 | E10: =H10/H10*100 -> 100 | F10: 30.55 | G10: =F10+2 -> 32.55 | H10: =D10*F10 -> 2452706.8 | I10: =D10*G10 -> 2613276.8 | J10: =I10-H10 -> 160570
A12: Insurance
A13: Jubilee | B13: Insurance | C13: 3.33 | D13: 4717 | E13: =H13/(SUM(H13:H15))*100 -> 51.53382 | F13: 360 | G13: =F13+2 -> 362 | H13: =D13*F13 -> 1698120 | I13: =D13*G13 -> 1707554 | J13: =I13-H13 -> 9434
A14: CIC | B14: Insurance | C14: 3.33 | D14: 195596 | E14: =H14/(SUM(H13:H15))*100 -> 24.871269 | F14: 4.19 | G14: =F14+2 -> 6.19 | H14: =D14*F14 -> 819547.24 | I14: =D14*G14 -> 1210739.2 | J14: =I14-H14 -> 391192
A15: Britam | B15: Insurance | C15: 3.34 | D15: 60505 | E15: =H15/(SUM(H13:H15))*100 -> 23.594911 | F15: 12.85 | G15: =F15+2 -> 14.85 | H15: =D15*F15 -> 777489.25 | I15: =D15*G15 -> 898499.25 | J15: =I15-H15 -> 121010
A17: Energy
A18: KenGen | B18: Energy | C18: 3.33 | D18: 99700 | E18: =H18/(SUM(H18:H20))*100 -> 22.844213 | F18: 9.18 | G18: =F18+2 -> 11.18 | H18: =D18*F18 -> 915246 | I18: =D18*G18 -> 1114646 | J18: =I18-H18 -> 199400
A19: Kenya Power | B19: Energy | C19: 3.33 | D19: 91836 | E19: =H19/(SUM(H18:H20))*100 -> 35.185174 | F19: 15.35 | G19: =F19+2 -> 17.35 | H19: =D19*F19 -> 1409682.6 | I19: =D19*G19 -> 1593354.6 | J19: =I19-H19 -> 183672
A20: Total Energies Marketing | B20: Energy | C20: 3.34 | D20: 30298 | E20: =H20/(SUM(H18:H20))*100 -> 41.970613 | F20: 55.5 | G20: =F20+2 -> 57.5 | H20: =D20*F20 -> 1681539 | I20: =D20*G20 -> 1742135 | J20: =I20-H20 -> 60596
A22: ETFs
A23: VOO / IVV | B23: ETF | C23: 10 | D23: 49 | E23: =H23/(SUM(H23:H24))*100 -> 69.712803 | F23: 52240 | G23: =F23+2 -> 52242 | H23: =D23*F23 -> 2559760 | I23: =D23*G23 -> 2559858 | J23: =I23-H23 -> 98
A24: VT | B24: ETF | C24: 5 | D24: 97 | E24: =H24/(SUM(H23:H24))*100 -> 30.287197 | F24: 11465 | G24: =F24+2 -> 11467 | H24: =D24*F24 -> 1112105 | I24: =D24*G24 -> 1112299 | J24: =I24-H24 -> 194
A26: Fixed Income
A27: Treasury Bonds | B27: Fixed Income | C27: 30 | D27: 121 | E27: =D27/D27*100 -> 100 | F27: 50000 | G27: =F27 -> 50000 | H27: =D27*F27 -> 6050000
A29: Liquid Cash
A30: Money Market Fund | B30: Cash | C30: 5 | D30: 2 | E30: =D30/D30*100 -> 100 | F30: 1000000 | G30: =F30 -> 1000000 | H30: =D30*F30 -> 2000000
A33: Sector Value
B34: Sector | C34: Total Value | D34: Portfolio Percentage | E34: Charts
B35: Banking | C35: =SUM(H4:H7) -> 4711965 | D35: =C35/C45*100 -> 17.99273
B36: Telecom | C36: =H10 -> 2452706.8 | D36: =C36/C45*100 -> 9.3657083
B37: Insurance | C37: =SUM(H13:H15) -> 3295156.5 | D37: =C37/C45*100 -> 12.582619
B38: Energy | C38: =SUM(H18:H20) -> 4006467.6 | D38: =C38/C45*100 -> 15.298774
B39: ETFs | C39: =SUM(H23:H24) -> 3671865 | D39: =C39/C45*100 -> 14.021088
B40: Fixed Income | C40: =H27 -> 6050000 | D40: =C40/C45*100 -> 23.102042
B41: Liquid Cash | C41: =H30 -> 2000000 | D41: =C41/C45*100 -> 7.6370388
B43: Kenyan-Stock Sector | C43: =SUM(C35:C38) -> 14466296
B45: Total Portfolio Value | C45: =SUM(C35:C41) -> 26188161

Sheet Dividend Tracking
A1: Date | B1: Asset | C1: Dividend per Share | D1: Shares | E1: Total Dividend
B2: Co-op | D2: =Holdings!D4 -> 33000
B3: Equity | D3: =Holdings!D5 -> 15000
B4: KCB | D4: =Holdings!D6 -> 18900
B5: NCBA | D5: =Holdings!D7 -> 14640
B6: Safaricom | D6: =Holdings!D10 -> 80285
B7: Jubilee | D7: =Holdings!D13 -> 4717
B8: CIC | D8: =Holdings!D14 -> 195596
B9: Britam Holdings | D9: =Holdings!D15 -> 60505
B10: KenGen | D10: =Holdings!D18 -> 99700
B11: KPLC | D11: =Holdings!D19 -> 91836
B12: Total Energies | D12: =Holdings!D20 -> 30298
B13: VOO/IVV | D13: =Holdings!D23 -> 49
B14: VT | D14: =Holdings!D24 -> 97

Sheet Dashboard1
A25: Sector | B25: Allocation %
A26: Banking | B26: 22.623431
A27: Cash | B27: 0
A28: ETF | B28: 19.118726
A29: Energy | B29: 11.10386
A30: Fixed Income | B30: 0
A31: Insurance | B31: 16.308517
A32: Telecom | B32: 16.684272
